phantomcollect/__init__.py
phantomcollect/core.py
phantomcollect/templates/collector.html
phantomcollect-1.0.0.dist-info/licenses/LICENSE
phantomcollect-1.0.0.dist-info/METADATA
phantomcollect-1.0.0.dist-info/WHEEL
phantomcollect-1.0.0.dist-info/entry_points.txt
phantomcollect-1.0.0.dist-info/top_level.txt
phantomcollect-1.0.0.dist-info/RECORD
