Metadata-Version: 2.4
Name: phantomcollect
Version: 1.0.0
Summary: Advanced Stealth Web Data Collection Framework
Home-page: https://github.com/xsser01/phantomcollect
Author: xsser01
Author-email: psosoej210@gmail.com
Keywords: security,web,data-collection,penetration-testing
Classifier: Programming Language :: Python :: 3
Classifier: License :: OSI Approved :: MIT License
Classifier: Operating System :: OS Independent
Classifier: Topic :: Security
Classifier: Topic :: Internet :: WWW/HTTP :: HTTP Servers
Requires-Python: >=3.6
License-File: LICENSE
Dynamic: author
Dynamic: author-email
Dynamic: classifier
Dynamic: description
Dynamic: description-content-type
Dynamic: home-page
Dynamic: keywords
Dynamic: license-file
Dynamic: requires-python
Dynamic: summary
